[{"id":25774742,"steamid64":"76561199106664098","player_name":"Alberto","steam_id":"STEAM_1:0:573199185","server_id":1748,"map_id":1264,"stage":8,"mode":"kz_timer","tickrate":128,"time":10.117,"teleports":0,"created_on":"2025-04-02T17:08:10","updated_on":"2025-04-02T17:08:10","updated_by":0,"place":1,"top_100":1,"top_100_overall":1,"server_name":"jumpstatters)","map_name":"skz_malaka","points":1000,"record_filter_id":0,"replay_id":0},{"id":25774314,"steamid64":"76561198198062889","player_name":"Dima","steam_id":"STEAM_1:1:118898580","server_id":1296,"map_id":1264,"stage":8,"mode":"kz_timer","tickrate":128,"time":10.242,"teleports":0,"created_on":"2025-04-02T15:35:07","updated_on":"2025-04-02T15:35:07","updated_by":0,"place":1,"top_100":1,"top_100_overall":1,"server_name":"KURBASHIGANG OFFICIAL KREEDZ SERVER VIP 18+","map_name":"skz_malaka","points":857,"record_filter_id":0,"replay_id":0},{"id":23818797,"steamid64":"76561198091592005","player_name":"Blacky","steam_id":"STEAM_1:1:65663138","server_id":1749,"map_id":852,"stage":8,"mode":"kz_timer","tickrate":128,"time":18.734,"teleports":0,"created_on":"2023-12-19T17:10:45","updated_on":"2023-12-19T17:10:45","updated_by":0,"place":1,"top_100":1,"top_100_overall":1,"server_name":"wheelchair","map_name":"kz_rush2sk8","points":1000,"record_filter_id":0,"replay_id":0},{"id":23053608,"steamid64":"76561199262637934","player_name":"我是2B","steam_id":"STEAM_1:0:651186103","server_id":1706,"map_id":1136,"stage":8,"mode":"kz_timer","tickrate":128,"time":5.953,"teleports":0,"created_on":"2023-09-10T10:30:10","updated_on":"2023-09-10T10:30:10","updated_by":0,"place":1,"top_100":1,"top_100_overall":1,"server_name":"5EPLAY KZ SERVER","map_name":"kz_communityblock","points":1000,"record_filter_id":0,"replay_id":0},{"id":18844085,"steamid64":"76561198103598339","player_name":"игорь скок над ды","steam_id":"STEAM_1:1:71666305","server_id":1372,"map_id":1136,"stage":8,"mode":"kz_timer","tickrate":128,"time":6.063,"teleports":0,"created_on":"2022-11-09T11:22:21","updated_on":"2022-11-09T11:22:21","updated_by":0,"place":1,"top_100":1,"top_100_overall":1,"server_name":"Kz #14 © cybershoke.net (Gokz, tier 1-2, Moscow)","map_name":"kz_communityblock","points":993,"record_filter_id":0,"replay_id":0},{"id":18074535,"steamid64":"76561198978804154","player_name":"cresc","steam_id":"STEAM_1:0:509269213","server_id":1068,"map_id":1129,"stage":8,"mode":"kz_timer","tickrate":128,"time":0.188,"teleports":0,"created_on":"2022-09-12T06:12:41","updated_on":"2022-09-12T06:12:41","updated_by":0,"place":1,"top_100":1,"top_100_overall":1,"server_name":"[GFLClan.com] KZ Climb #2","map_name":"kz_gluttony","points":1000,"record_filter_id":0,"replay_id":0},{"id":17311967,"steamid64":"76561198097865637","player_name":"LEO","steam_id":"STEAM_1:1:68799954","server_id":839,"map_id":1010,"stage":8,"mode":"kz_timer","tickrate":128,"time":5.594,"teleports":0,"created_on":"2022-07-22T04:15:17","updated_on":"2022-07-22T04:15:17","updated_by":0,"place":1,"top_100":1,"top_100_overall":1,"server_name":"GMZ's Server","map_name":"kz_holdmyhand","points":1000,"record_filter_id":0,"replay_id":0},{"id":16634994,"steamid64":"76561198203824899","player_name":"Rumble","steam_id":"STEAM_1:1:121779585","server_id":1351,"map_id":1130,"stage":8,"mode":"kz_timer","tickrate":128,"time":5.375,"teleports":0,"created_on":"2022-05-28T21:47:50","updated_on":"2022-05-28T21:47:50","updated_by":0,"place":1,"top_100":1,"top_100_overall":1,"server_name":"BrutalCS - GOKZ 128T  01","map_name":"kz_sp1_spreadblocks","points":1000,"record_filter_id":0,"replay_id":0},{"id":16560704,"steamid64":"76561198015267733","player_name":"panda","steam_id":"STEAM_1:1:27501002","server_id":1064,"map_id":1136,"stage":8,"mode":"kz_timer","tickrate":128,"time":6.164,"teleports":0,"created_on":"2022-05-22T21:57:23","updated_on":"2022-05-22T21:57:23","updated_by":0,"place":1,"top_100":1,"top_100_overall":1,"server_name":"[EU] CawKZ Kreedz VIP #2","map_name":"kz_communityblock","points":984,"record_filter_id":0,"replay_id":0},{"id":16098936,"steamid64":"76561198162042783","player_name":"Invers","steam_id":"STEAM_1:1:100888527","server_id":1000,"map_id":1136,"stage":8,"mode":"kz_timer","tickrate":128,"time":6.531,"teleports":0,"created_on":"2022-04-16T23:59:31","updated_on":"2022-04-16T23:59:31","updated_by":0,"place":1,"top_100":1,"top_100_overall":1,"server_name":"[EU] CawKZ Kreedz VIP #6","map_name":"kz_communityblock","points":937,"record_filter_id":0,"replay_id":0},{"id":16067554,"steamid64":"76561198219579692","player_name":"KaKa47","steam_id":"STEAM_1:0:129656982","server_id":883,"map_id":1136,"stage":8,"mode":"kz_timer","tickrate":128,"time":6.906,"teleports":0,"created_on":"2022-04-13T23:38:48","updated_on":"2022-04-13T23:38:48","updated_by":0,"place":1,"top_100":1,"top_100_overall":1,"server_name":"[EU] CawKZ Kreedz VIP #3","map_name":"kz_communityblock","points":850,"record_filter_id":0,"replay_id":0},{"id":16019867,"steamid64":"76561198051108171","player_name":"Jak","steam_id":"STEAM_1:1:45421221","server_id":538,"map_id":1130,"stage":8,"mode":"kz_timer","tickrate":128,"time":5.586,"teleports":0,"created_on":"2022-04-10T20:11:26","updated_on":"2022-04-10T20:11:26","updated_by":0,"place":1,"top_100":1,"top_100_overall":1,"server_name":"Loaf of Bread #7 VIP/50%","map_name":"kz_sp1_spreadblocks","points":989,"record_filter_id":0,"replay_id":0},{"id":16009890,"steamid64":"76561198194803245","player_name":"neon","steam_id":"STEAM_1:1:117268758","server_id":1346,"map_id":1130,"stage":8,"mode":"kz_timer","tickrate":128,"time":6.188,"teleports":0,"created_on":"2022-04-10T05:26:09","updated_on":"2022-04-10T05:26:09","updated_by":0,"place":1,"top_100":1,"top_100_overall":1,"server_name":"going slow","map_name":"kz_sp1_spreadblocks","points":931,"record_filter_id":0,"replay_id":0},{"id":15726843,"steamid64":"76561198117362046","player_name":"GMZ","steam_id":"STEAM_1:0:78548159","server_id":839,"map_id":1129,"stage":8,"mode":"kz_timer","tickrate":128,"time":0.328,"teleports":0,"created_on":"2022-03-16T20:04:34","updated_on":"2022-03-16T20:04:34","updated_by":0,"place":1,"top_100":1,"top_100_overall":1,"server_name":"GMZ's Server","map_name":"kz_gluttony","points":947,"record_filter_id":0,"replay_id":0},{"id":15677661,"steamid64":"76561198086996631","player_name":"Icarus","steam_id":"STEAM_1:1:63365451","server_id":1503,"map_id":1129,"stage":8,"mode":"kz_timer","tickrate":128,"time":0.383,"teleports":0,"created_on":"2022-03-13T15:36:03","updated_on":"2022-03-13T15:36:03","updated_by":0,"place":1,"top_100":1,"top_100_overall":1,"server_name":"ZA Community Climb GOKZ (Global times, 128 tick)","map_name":"kz_gluttony","points":896,"record_filter_id":0,"replay_id":0},{"id":15673951,"steamid64":"76561198051108171","player_name":"Jak","steam_id":"STEAM_1:1:45421221","server_id":664,"map_id":1129,"stage":8,"mode":"kz_timer","tickrate":128,"time":21.641,"teleports":0,"created_on":"2022-03-13T11:50:35","updated_on":"2022-03-13T11:50:35","updated_by":0,"place":1,"top_100":1,"top_100_overall":1,"server_name":"Loaf of Bread #6 VIP/30%","map_name":"kz_gluttony","points":124,"record_filter_id":0,"replay_id":0},{"id":15673143,"steamid64":"76561198272375112","player_name":"i see you clearly","steam_id":"STEAM_1:0:156054692","server_id":664,"map_id":1129,"stage":8,"mode":"kz_timer","tickrate":128,"time":23.070,"teleports":0,"created_on":"2022-03-13T11:06:17","updated_on":"2022-03-13T11:06:17","updated_by":0,"place":1,"top_100":1,"top_100_overall":1,"server_name":"Loaf of Bread #6 VIP/30%","map_name":"kz_gluttony","points":121,"record_filter_id":0,"replay_id":0},{"id":15672661,"steamid64":"76561198072316325","player_name":"taoz1","steam_id":"STEAM_1:1:56025298","server_id":1419,"map_id":1129,"stage":8,"mode":"kz_timer","tickrate":128,"time":24.750,"teleports":0,"created_on":"2022-03-13T10:45:38","updated_on":"2022-03-13T10:45:38","updated_by":0,"place":1,"top_100":1,"top_100_overall":1,"server_name":"GOKZ.NET T3-T5","map_name":"kz_gluttony","points":117,"record_filter_id":0,"replay_id":0},{"id":15665687,"steamid64":"76561198111364954","player_name":"modas","steam_id":"STEAM_1:0:75549613","server_id":1243,"map_id":1129,"stage":8,"mode":"kz_timer","tickrate":128,"time":26.086,"teleports":0,"created_on":"2022-03-12T23:52:42","updated_on":"2022-03-12T23:52:42","updated_by":0,"place":1,"top_100":1,"top_100_overall":1,"server_name":"¦¦ [PL] » GGEASY.pl « [ GOKZ ] Tick128","map_name":"kz_gluttony","points":115,"record_filter_id":0,"replay_id":0},{"id":13321013,"steamid64":"76561198117362046","player_name":"GMZ","steam_id":"STEAM_1:0:78548159","server_id":839,"map_id":1010,"stage":8,"mode":"kz_timer","tickrate":128,"time":5.633,"teleports":0,"created_on":"2021-08-14T02:59:54","updated_on":"2021-08-14T02:59:54","updated_by":0,"place":1,"top_100":1,"top_100_overall":1,"server_name":"GMZ's Server","map_name":"kz_holdmyhand","points":995,"record_filter_id":0,"replay_id":0},{"id":13215744,"steamid64":"76561197973698265","player_name":"ゼーリエ","steam_id":"STEAM_1:1:6716268","server_id":839,"map_id":1010,"stage":8,"mode":"kz_timer","tickrate":128,"time":5.648,"teleports":0,"created_on":"2021-08-06T05:15:40","updated_on":"2021-08-06T05:15:40","updated_by":0,"place":1,"top_100":1,"top_100_overall":1,"server_name":"GMZ's Server","map_name":"kz_holdmyhand","points":993,"record_filter_id":0,"replay_id":0},{"id":13207561,"steamid64":"76561198199601203","player_name":"Avt = D","steam_id":"STEAM_1:1:119667737","server_id":1329,"map_id":1010,"stage":8,"mode":"kz_timer","tickrate":128,"time":5.727,"teleports":0,"created_on":"2021-08-05T17:28:25","updated_on":"2021-08-05T17:28:25","updated_by":0,"place":1,"top_100":1,"top_100_overall":1,"server_name":"Esterata.com | KZ - VIP #4 - EU/FI","map_name":"kz_holdmyhand","points":990,"record_filter_id":0,"replay_id":0},{"id":12813098,"steamid64":"76561197973698265","player_name":"ゼーリエ","steam_id":"STEAM_1:1:6716268","server_id":839,"map_id":589,"stage":8,"mode":"kz_timer","tickrate":128,"time":10.094,"teleports":0,"created_on":"2021-07-02T05:27:56","updated_on":"2021-07-02T05:27:56","updated_by":0,"place":1,"top_100":1,"top_100_overall":1,"server_name":"GMZ's Server","map_name":"skz_makalaka","points":1000,"record_filter_id":0,"replay_id":0},{"id":9894881,"steamid64":"76561198051108171","player_name":"Jak","steam_id":"STEAM_1:1:45421221","server_id":664,"map_id":852,"stage":8,"mode":"kz_timer","tickrate":128,"time":19.781,"teleports":0,"created_on":"2021-01-08T16:29:29","updated_on":"2021-01-08T16:29:29","updated_by":0,"place":1,"top_100":1,"top_100_overall":1,"server_name":"Loaf of Bread #6 VIP/30%","map_name":"kz_rush2sk8","points":904,"record_filter_id":0,"replay_id":0},{"id":8492026,"steamid64":"76561198102813830","player_name":"Jiwon","steam_id":"STEAM_1:0:71274051","server_id":1011,"map_id":852,"stage":8,"mode":"kz_timer","tickrate":128,"time":21.906,"teleports":0,"created_on":"2020-10-08T09:23:27","updated_on":"2020-10-08T09:23:27","updated_by":0,"place":1,"top_100":1,"top_100_overall":1,"server_name":"Botak's Private GOKZ","map_name":"kz_rush2sk8","points":761,"record_filter_id":0,"replay_id":0},{"id":8491866,"steamid64":"76561198883151102","player_name":"VENIGA STEPHANO","steam_id":"STEAM_1:0:461442687","server_id":1011,"map_id":852,"stage":8,"mode":"kz_timer","tickrate":128,"time":23.477,"teleports":0,"created_on":"2020-10-08T09:06:44","updated_on":"2020-10-08T09:06:44","updated_by":0,"place":1,"top_100":1,"top_100_overall":1,"server_name":"Botak's Private GOKZ","map_name":"kz_rush2sk8","points":666,"record_filter_id":0,"replay_id":0},{"id":7734706,"steamid64":"76561198063573203","player_name":"alves","steam_id":"STEAM_1:1:51653737","server_id":948,"map_id":589,"stage":8,"mode":"kz_timer","tickrate":128,"time":10.422,"teleports":0,"created_on":"2020-08-22T04:54:26","updated_on":"2020-08-22T04:54:26","updated_by":0,"place":1,"top_100":1,"top_100_overall":1,"server_name":"Ni Una Menos KZ","map_name":"skz_makalaka","points":982,"record_filter_id":0,"replay_id":0},{"id":5014250,"steamid64":"76561198097865637","player_name":"LEO","steam_id":"STEAM_1:1:68799954","server_id":376,"map_id":589,"stage":8,"mode":"kz_timer","tickrate":128,"time":11.625,"teleports":0,"created_on":"2020-02-19T10:16:18","updated_on":"2020-02-19T10:16:18","updated_by":0,"place":1,"top_100":1,"top_100_overall":1,"server_name":"KZ/CLIMB @ Registre-se GamersClub.com.br","map_name":"skz_makalaka","points":909,"record_filter_id":0,"replay_id":0},{"id":4669674,"steamid64":"76561198033965034","player_name":"Packert","steam_id":"STEAM_1:0:36849653","server_id":523,"map_id":589,"stage":8,"mode":"kz_timer","tickrate":128,"time":13.203,"teleports":0,"created_on":"2020-01-17T13:25:04","updated_on":"2020-01-17T13:25:04","updated_by":0,"place":1,"top_100":1,"top_100_overall":1,"server_name":"Packerts jump server","map_name":"skz_makalaka","points":730,"record_filter_id":0,"replay_id":0},{"id":4669227,"steamid64":"76561198165203332","player_name":"GameChaos","steam_id":"STEAM_1:0:102468802","server_id":523,"map_id":589,"stage":8,"mode":"kz_timer","tickrate":128,"time":13.820,"teleports":0,"created_on":"2020-01-17T12:36:19","updated_on":"2020-01-17T12:36:19","updated_by":0,"place":1,"top_100":1,"top_100_overall":1,"server_name":"Packerts jump server","map_name":"skz_makalaka","points":648,"record_filter_id":0,"replay_id":0}]